src/pypomes_scheduling/__init__.py
src/pypomes_scheduling/scheduling_pomes.py
src/pypomes_scheduling/threaded_scheduler.py
pypomes_sccheduling-0.1.1.dist-info/METADATA
pypomes_sccheduling-0.1.1.dist-info/WHEEL
pypomes_sccheduling-0.1.1.dist-info/licenses/LICENSE
pypomes_sccheduling-0.1.1.dist-info/RECORD
