Metadata-Version: 2.1
Name: pypomes_sccheduling
Version: 0.1.1
Summary: A collection of Python pomes, pennyeach (scheduling module)
Project-URL: Homepage, https://github.com/TheWiseCoder/PyPomes-Scheduling
Project-URL: Bug Tracker, https://github.com/TheWiseCoder/PyPomes-Scheduling/issues
Author-email: GT Nunes <wisecoder01@gmail.com>
License-File: LICENSE
Classifier: License :: OSI Approved :: MIT License
Classifier: Operating System :: OS Independent
Classifier: Programming Language :: Python :: 3
Requires-Python: >=3.10
Requires-Dist: apscheduler>=3.10.1
Requires-Dist: pip>=23.1.2
Requires-Dist: pypomes-core>=0.1.4
Requires-Dist: setuptools>=68.0.0
Requires-Dist: wheel>=0.40.0
